odoo/addons/hr_course/README.rst
odoo/addons/hr_course/__init__.py
odoo/addons/hr_course/__manifest__.py
odoo/addons/hr_course/data/ir_cron_data.xml
odoo/addons/hr_course/data/mail_channel.xml
odoo/addons/hr_course/data/mail_template.xml
odoo/addons/hr_course/demo/hr_course.xml
odoo/addons/hr_course/i18n/de.po
odoo/addons/hr_course/i18n/es.po
odoo/addons/hr_course/i18n/fr.po
odoo/addons/hr_course/i18n/hr_course.pot
odoo/addons/hr_course/i18n/it.po
odoo/addons/hr_course/i18n/pt.po
odoo/addons/hr_course/i18n/pt_BR.po
odoo/addons/hr_course/migrations/14.0.2.0.0/noupdate_changes.xml
odoo/addons/hr_course/migrations/14.0.2.0.0/post-migration.py
odoo/addons/hr_course/migrations/14.0.2.0.0/pre-migration.py
odoo/addons/hr_course/models/__init__.py
odoo/addons/hr_course/models/hr_course.py
odoo/addons/hr_course/models/hr_course_attendee.py
odoo/addons/hr_course/models/hr_course_category.py
odoo/addons/hr_course/models/hr_course_schedule.py
odoo/addons/hr_course/models/hr_employee.py
odoo/addons/hr_course/models/res_company.py
odoo/addons/hr_course/models/res_config_settings.py
odoo/addons/hr_course/readme/CONTRIBUTORS.rst
odoo/addons/hr_course/readme/DESCRIPTION.rst
odoo/addons/hr_course/readme/USAGE.rst
odoo/addons/hr_course/security/course_security.xml
odoo/addons/hr_course/security/ir.model.access.csv
odoo/addons/hr_course/static/description/icon.png
odoo/addons/hr_course/static/description/index.html
odoo/addons/hr_course/tests/__init__.py
odoo/addons/hr_course/tests/test_hr_course.py
odoo/addons/hr_course/views/hr_course_category_views.xml
odoo/addons/hr_course/views/hr_course_schedule_views.xml
odoo/addons/hr_course/views/hr_course_views.xml
odoo/addons/hr_course/views/hr_employee_views.xml
odoo/addons/hr_course/views/hr_settings.xml
odoo14_addon_hr_course-14.0.3.1.1.dist-info/METADATA
odoo14_addon_hr_course-14.0.3.1.1.dist-info/WHEEL
odoo14_addon_hr_course-14.0.3.1.1.dist-info/top_level.txt
odoo14_addon_hr_course-14.0.3.1.1.dist-info/RECORD
